<?xml version='1.0' encoding='UTF-8'?>
<tas:taskFormUiContext xmlns:tas="http://xmlns.oracle.com/taskformui">
   <tas:taskFormName>Crear_Comunicacion</tas:taskFormName>
   <tas:taskFlowName>HT_Crear_Comunicacion_TaskFlow</tas:taskFlowName>
   <tas:templateType>packaged</tas:templateType>
   <tas:packagedTemplate>default</tas:packagedTemplate>
   <tas:header>
      <tas:headerCustomActions>true</tas:headerCustomActions>
      <tas:headerSystemActions>true</tas:headerSystemActions>
      <tas:headerColumnCount>1</tas:headerColumnCount>
      <tas:headerAttribList/>
   </tas:header>
   <tas:body>
      <tas:title/>
      <tas:rowList>
         <tas:row>
            <tas:column>
               <tas:attrib>ComunicacionSalidaBO.fechaCreacion</tas:attrib>
               <tas:attrib>ComunicacionSalidaBO.fechaRadicacion</tas:attrib>
               <tas:attrib>ComunicacionSalidaBO.nroRadicado</tas:attrib>
               <tas:attrib>ComunicacionSalidaBO.esTituloMinero</tas:attrib>
               <tas:attrib>ComunicacionSalidaBO.placa</tas:attrib>
               <tas:attrib>ComunicacionSalidaBO.referencia</tas:attrib>
               <tas:attrib>ComunicacionSalidaBO.asunto</tas:attrib>
               <tas:attrib>ComunicacionSalidaBO.nroFolios</tas:attrib>
               <tas:attrib>ComunicacionSalidaBO.nroAnexos</tas:attrib>
               <tas:attrib>ComunicacionSalidaBO.medioEnvio</tas:attrib>
               <tas:attrib>ComunicacionSalidaBO.nroRadicadoRelacionado</tas:attrib>
               <tas:attrib>ComunicacionSalidaBO.anexos.nombre</tas:attrib>
               <tas:attrib>ComunicacionSalidaBO.anexos.descripcion</tas:attrib>
               <tas:attrib>ComunicacionSalidaBO.anexos.contenido</tas:attrib>
               <tas:attrib>ComunicacionSalidaBO.anexos.mimeType</tas:attrib>
               <tas:attrib>ComunicacionSalidaBO.anexos.tipoAnexo</tas:attrib>
               <tas:attrib>ComunicacionSalidaBO.interesadosExternos.id</tas:attrib>
               <tas:attrib>ComunicacionSalidaBO.interesadosExternos.tipoIdentificacion</tas:attrib>
               <tas:attrib>ComunicacionSalidaBO.interesadosExternos.nroIdentificacion</tas:attrib>
               <tas:attrib>ComunicacionSalidaBO.interesadosExternos.nombre</tas:attrib>
               <tas:attrib>ComunicacionSalidaBO.interesadosExternos.telefono</tas:attrib>
               <tas:attrib>ComunicacionSalidaBO.interesadosExternos.email</tas:attrib>
               <tas:attrib>ComunicacionSalidaBO.interesadosExternos.direccionCorrespondencia</tas:attrib>
               <tas:attrib>UsuarioBO.idUsuario</tas:attrib>
               <tas:attrib>UsuarioBO.codDependencia</tas:attrib>
               <tas:attrib>UsuarioBO.email</tas:attrib>
               <tas:attrib>UsuarioBO.nombre</tas:attrib>
               <tas:attrib>UsuarioBO.rol</tas:attrib>
            </tas:column>
         </tas:row>
      </tas:rowList>
   </tas:body>
   <tas:footer>
      <tas:comments>false</tas:comments>
      <tas:attachments>true</tas:attachments>
      <tas:history>false</tas:history>
   </tas:footer>
</tas:taskFormUiContext>
